modusa/__init__.py
modusa/animate/__init__.py
modusa/animate/animate.py
modusa/assets/fonts/NotoSansDevanagari-Regular.ttf
modusa/assets/images/icon.png
modusa/create/__init__.py
modusa/create/figure/__init__.py
modusa/create/figure/_sharedutils.py
modusa/create/figure/collage.py
modusa/create/figure/deck.py
modusa/create/figure/tracks.py
modusa/create/tool/__init__.py
modusa/create/tool/bp_marker.py
modusa/extract/__init__.py
modusa/extract/stft.py
modusa/junk/audio/__init__.py
modusa/junk/audio/audio.py
modusa/junk/audio/utils.py
modusa/load/__init__.py
modusa/load/audacity_labels.py
modusa/load/audio.py
modusa/load/ctm.py
modusa/load/image.py
modusa/load/loader.py
modusa/load/textgrid.py
modusa/models/__init__.py
modusa/models/annotation.py
modusa/paint/__init__.py
modusa/paint/annotation.py
modusa/paint/arrow.py
modusa/paint/events.py
modusa/paint/hill.py
modusa/paint/image.py
modusa/paint/line.py
modusa/paint/polygon.py
modusa/paint/signal.py
modusa/play/__init__.py
modusa/play/audio.py
modusa/probe/__init__.py
modusa/probe/audio.py
modusa/record/__init__.py
modusa/record/audio.py
modusa/save/__init__.py
modusa/save/annotation/__init__.py
modusa/save/annotation/as_audacity_labels.py
modusa/save/annotation/as_ctm.py
modusa/save/annotation/as_textgrid.py
modusa/set/__init__.py
modusa/set/view/__init__.py
modusa/set/view/fig_title.py
modusa/set/view/gridlines.py
modusa/set/view/label.py
modusa/set/view/legend.py
modusa/set/view/limit.py
modusa/set/view/ticks.py
modusa/set/view/title.py
modusa/sonify/__init__.py
modusa/sonify/f0_contour.py
modusa/sonify/onsets.py
modusa/utils/__init__.py
modusa/utils/audio_converter.py
modusa/utils/youtube_downloader.py
modusa-5.0.3.dist-info/METADATA
modusa-5.0.3.dist-info/WHEEL
modusa-5.0.3.dist-info/licenses/LICENSE.md
modusa-5.0.3.dist-info/RECORD
