Metadata-Version: 2.4
Name: modusa
Version: 5.0.3
Summary: A modular signal analysis python library.
Author-email: Ankit Anand <ankit0.anand0@gmail.com>
License: MIT
License-File: LICENSE.md
Requires-Python: >=3.11
Requires-Dist: imageio-ffmpeg>=0.6.0
Requires-Dist: imageio>=2.37.0
Requires-Dist: ipympl>=0.9.8
Requires-Dist: ipython>=9.5.0
Requires-Dist: ipywidgets>=8.1.7
Requires-Dist: matplotlib>=3.10.3
Requires-Dist: numpy>=2.2.6
Requires-Dist: sounddevice>=0.5.2
